{
  "id": "AP-2021-Fall-AM-45",
  "qNo": 45,
  "text": "化学製品を製造する化学プラントに、情報ネットワークと制御ネットワークがある。この二つのネットワークを接続し、その境界に、制御ネットワークのセキュリティを高めるために DMZを構築し、制御ネットワーク内の機器のうち、情報ネットワークとの通信が必要なものをこのDMZ に移した。DMZに移した機器はどれか。",
  "options": [
    {
      "id": "a",
      "text": "温度,流量,圧力などを計測するセンサ"
    },
    {
      "id": "b",
      "text": "コントローラからの測定値を監視し、設定値(目標値)を入力する操作端末"
    },
    {
      "id": "c",
      "text": "センサからの測定値が設定値に一致するように調整するコントローラ"
    },
    {
      "id": "d",
      "text": "定期的にソフトウェアをアップデートする機器に対して、情報ネットワークから入手したアップデートソフトウェアを提供するパッチ管理サーバ"
    }
  ],
  "correctOption": "d",
  "explanation": "",
  "examId": "AP-2021-Fall-AM"
}