[
  {
    "qNo": 1,
    "text": "送信者から受信者にメッセージ認証符号 (MAC: Message Authentication Code) を付与したメッセージを送り、さらに受信者が第三者に転送した。そのときの MAC に関する記述のうち、適切なものはどれか。ここで、共通鍵は送信者と受信者だけが知っており、送信者と受信者のそれぞれの公開鍵は3人とも知っているとする。",
    "options": [
      {
        "id": "a",
        "text": "MAC は、送信者がメッセージと共通鍵を用いて生成する。MAC を用いると、受信者がメッセージの完全性を確認できる。"
      },
      {
        "id": "b",
        "text": "MAC は、送信者がメッセージと共通鍵を用いて生成する。MAC を用いると、第三者が送信者の真正性を確認できる。"
      },
      {
        "id": "c",
        "text": "MAC は、送信者がメッセージと受信者の公開鍵を用いて生成する。MAC を用いると、第三者がメッセージの完全性を確認できる。"
      },
      {
        "id": "d",
        "text": "MAC は、送信者がメッセージと送信者の公開鍵を用いて生成する。MAC を用いると、受信者が送信者の真正性を確認できる。"
      }
    ],
    "correctOption": null,
    "subCategory": "その他"
  },
  {
    "qNo": 2,
    "text": "PKI (公開鍵基盤) を構成する RA (Registration Authority) の役割はどれか。",
    "options": [
      {
        "id": "a",
        "text": "デジタル証明書にデジタル署名を付与する。"
      },
      {
        "id": "b",
        "text": "デジタル証明書に紐づけられた属性証明書を発行する。"
      },
      {
        "id": "c",
        "text": "デジタル証明書の失効リストを管理し、デジタル証明書の有効性を確認する。"
      },
      {
        "id": "d",
        "text": "本人確認を行い、デジタル証明書の発行申請の承認又は却下を行う。"
      }
    ],
    "correctOption": null,
    "subCategory": "その他"
  },
  {
    "qNo": 3,
    "text": "標準化団体 OASIS が、Web サイトなどを運営するオンラインビジネスパートナー間で認証,属性及び認可の情報を安全に交換するために策定したものはどれか。",
    "options": [
      {
        "id": "a",
        "text": "SAML"
      },
      {
        "id": "b",
        "text": "SOAP"
      },
      {
        "id": "c",
        "text": "XKMS"
      },
      {
        "id": "d",
        "text": "XML Signature"
      }
    ],
    "correctOption": null,
    "subCategory": "その他"
  },
  {
    "qNo": 4,
    "text": "DoS攻撃の一つである Smurf 攻撃はどれか。",
    "options": [
      {
        "id": "a",
        "text": "TCP 接続要求である SYN パケットを攻撃対象に大量に送り付ける。"
      },
      {
        "id": "b",
        "text": "偽装した ICMP の要求パケットを送って、大量の応答パケットが攻撃対象に送られるようにする。"
      },
      {
        "id": "c",
        "text": "サイズが大きい UDPパケットを攻撃対象に大量に送り付ける。"
      },
      {
        "id": "d",
        "text": "サイズが大きい電子メールや大量の電子メールを攻撃対象に送り付ける。"
      }
    ],
    "correctOption": null,
    "subCategory": "その他"
  },
  {
    "qNo": 5,
    "text": "送信元 IP アドレスが A, 送信元ポート番号が 80/tcp, 宛先 IP アドレスが未使用の IP アドレス空間内の IP アドレスである SYN/ACK パケットを大量に観測した場合,推定できる攻撃はどれか。",
    "options": [
      {
        "id": "a",
        "text": "IP アドレス A を攻撃先とするサービス妨害攻撃"
      },
      {
        "id": "b",
        "text": "IP アドレス A を攻撃先とするパスワードリスト攻撃"
      },
      {
        "id": "c",
        "text": "IP アドレス A を攻撃元とするサービス妨害攻撃"
      },
      {
        "id": "d",
        "text": "IP アドレス A を攻撃元とするパスワードリスト攻撃"
      }
    ],
    "correctOption": null,
    "subCategory": "その他"
  },
  {
    "qNo": 6,
    "text": "パスワードスプレー攻撃に該当するものはどれか。",
    "options": [
      {
        "id": "a",
        "text": "攻撃対象とする利用者 ID を一つ定め、辞書及び人名リストに掲載されている単語及び人名並びにそれらの組合せを順にパスワードとして入力して、ログインを試行する。"
      },
      {
        "id": "b",
        "text": "攻撃対象とする利用者 ID を一つ定め、パスワードを総当たりして、ログインを試行する。"
      },
      {
        "id": "c",
        "text": "攻撃の時刻と攻撃元 IP アドレスとを変え、かつ、アカウントロックを回避しながらよく用いられるパスワードを複数の利用者 ID に同時に試し、ログインを試行する。"
      },
      {
        "id": "d",
        "text": "不正に取得したある他のサイトの利用者 ID とパスワードとの組みの一覧表を用いて, ログインを試行する。"
      }
    ],
    "correctOption": null,
    "subCategory": "その他"
  },
  {
    "qNo": 7,
    "text": "シングルサインオン (SSO) に関する記述のうち、適切なものはどれか。",
    "options": [
      {
        "id": "a",
        "text": "SAML 方式では、インターネット上の複数の Web サイトにおける SSO を、IdP (Identity Provider) で自動生成された URL 形式の1人一つの利用者 ID で実現する。"
      },
      {
        "id": "b",
        "text": "エージェント方式では、クライアント PC に導入したエージェントが SSO の対象システムのログイン画面を監視し、ログイン画面が表示されたら認証情報を代行入力する。"
      },
      {
        "id": "c",
        "text": "代理認証方式では、SSO の対象サーバに SSO のモジュールを組み込む必要があり, システムの改修が必要となる。"
      },
      {
        "id": "d",
        "text": "リバースプロキシ方式では、SSO を利用する全てのトラフィックがリバースプロキシサーバに集中し、リバースプロキシサーバが単一障害点になり得る。"
      }
    ],
    "correctOption": null,
    "subCategory": "その他"
  },
  {
    "qNo": 8,
    "text": "前方秘匿性 (Forward Secrecy) の説明として、適切なものはどれか。",
    "options": [
      {
        "id": "a",
        "text": "鍵交換に使った秘密鍵が漏えいしたとしても、それより前の暗号文は解読されない。"
      },
      {
        "id": "b",
        "text": "時系列データをチェーンの形で結び、かつ、ネットワーク上の複数のノードで共有するので、データを改ざんできない。"
      },
      {
        "id": "c",
        "text": "対となる二つの鍵の片方の鍵で暗号化したデータは、もう片方の鍵でだけ復号できる。"
      },
      {
        "id": "d",
        "text": "データに非可逆処理をして生成される固定長のハッシュ値からは、元のデータを推測できない。"
      }
    ],
    "correctOption": null,
    "subCategory": "その他"
  },
  {
    "qNo": 9,
    "text": "IT 製品及びシステムが、必要なセキュリティレベルを満たしているかどうかについて、調達者が判断する際に役立つ評価結果を提供し、独立したセキュリティ評価結果間の比較を可能にするための規格はどれか。",
    "options": [
      {
        "id": "a",
        "text": "ISO/IEC 15408"
      },
      {
        "id": "b",
        "text": "ISO/IEC 27002"
      },
      {
        "id": "c",
        "text": "ISO/IEC 27017"
      },
      {
        "id": "d",
        "text": "ISO/IEC 30147"
      }
    ],
    "correctOption": null,
    "subCategory": "その他"
  },
  {
    "qNo": 10,
    "text": "セキュリティ対策として、CASB (Cloud Access Security Broker) を利用した際の効果はどれか。",
    "options": [
      {
        "id": "a",
        "text": "クラウドサービスプロバイダが、運用しているクラウドサービスに対して、CASB を利用して DDoS 攻撃対策を行うことによって、クラウドサービスの可用性低下を緩和できる。"
      },
      {
        "id": "b",
        "text": "クラウドサービスプロバイダが、クラウドサービスを運用している施設に対して, CASB を利用して入退室管理を行うことによって、クラウドサービス運用環境への物理的な不正アクセスを防止できる。"
      },
      {
        "id": "c",
        "text": "クラウドサービス利用組織の管理者が、従業員が利用しているクラウドサービスに対して、CASB を利用して脆弱性診断を行うことによって、脆弱性を特定できる。"
      },
      {
        "id": "d",
        "text": "クラウドサービス利用組織の管理者が、従業員が利用しているクラウドサービスに対して、CASB を利用して利用状況の可視化を行うことによって、許可を得ずにクラウドサービスを利用している者を特定できる。"
      }
    ],
    "correctOption": null,
    "subCategory": "その他"
  },
  {
    "qNo": 11,
    "text": "クリックジャッキング攻撃に有効な対策はどれか。",
    "options": [
      {
        "id": "a",
        "text": "cookieに、 HttpOnly 属性を設定する。"
      },
      {
        "id": "b",
        "text": "cookieに, Secure 属性を設定する。"
      },
      {
        "id": "c",
        "text": "HTTP レスポンスヘッダーに、 Strict-Transport-Security を設定する。"
      },
      {
        "id": "d",
        "text": "HTTP レスポンスヘッダーに, X-Frame-Options を設定する。"
      }
    ],
    "correctOption": null,
    "subCategory": "その他"
  },
  {
    "qNo": 12,
    "text": "ブロックチェーンに関する記述のうち、適切なものはどれか。",
    "options": [
      {
        "id": "a",
        "text": "RADIUS を必須の技術として、参加者の利用者認証を一元管理するために利用する。"
      },
      {
        "id": "b",
        "text": "SPF を必須の技術として、参加者間で電子メールを送受信するときに送信元の真正性を確認するために利用する。"
      },
      {
        "id": "c",
        "text": "楕円曲線暗号を必須の技術として、参加者間の P2P (Peer to Peer) 通信を暗号化するために利用する。"
      },
      {
        "id": "d",
        "text": "ハッシュ関数を必須の技術として、参加者がデータの改ざんを検出するために利用する。"
      }
    ],
    "correctOption": null,
    "subCategory": "その他"
  },
  {
    "qNo": 13,
    "text": "PC からサーバに対し, IPv6 を利用した通信を行う場合、ネットワーク層で暗号化を行うときに利用するものはどれか。",
    "options": [
      {
        "id": "a",
        "text": "IPsec"
      },
      {
        "id": "b",
        "text": "PPP"
      },
      {
        "id": "c",
        "text": "SSH"
      },
      {
        "id": "d",
        "text": "TLS"
      }
    ],
    "correctOption": null,
    "subCategory": "その他"
  },
  {
    "qNo": 14,
    "text": "SMTP-AUTH の特徴はどれか。",
    "options": [
      {
        "id": "a",
        "text": "ISP 管理下の動的 IP アドレスから管理外ネットワークのメールサーバへの SMTP 接続を禁止する。"
      },
      {
        "id": "b",
        "text": "電子メール送信元のメールサーバが送信元ドメインの DNS に登録されていることを確認してから、電子メールを受信する。"
      },
      {
        "id": "c",
        "text": "メールクライアントからメールサーバへの電子メール送信時に、利用者 ID とパスワードなどによる利用者認証を行う。"
      },
      {
        "id": "d",
        "text": "メールクライアントからメールサーバへの電子メール送信は、POP 接続で利用者認証済みの場合にだけ許可する。"
      }
    ],
    "correctOption": null,
    "subCategory": "その他"
  },
  {
    "qNo": 15,
    "text": "SPF によるドメイン認証を実施する場合、SPF の導入時に、電子メール送信元アドレスのドメイン所有者側で行う必要がある設定はどれか。",
    "options": [
      {
        "id": "a",
        "text": "DNS サーバに SPF レコードを登録する。"
      },
      {
        "id": "b",
        "text": "DNS の問合せを受け付けるポート番号を変更する。"
      },
      {
        "id": "c",
        "text": "メールサーバにデジタル証明書を導入する。"
      },
      {
        "id": "d",
        "text": "メールサーバの TCP ポート 25 番を利用不可にする。"
      }
    ],
    "correctOption": null,
    "subCategory": "その他"
  },
  {
    "qNo": 16,
    "text": "電子メール又はその通信を暗号化する三つのプロトコルについて、公開鍵を用意する単位の組合せのうち、適切なものはどれか。[表参照]",
    "options": [
      {
        "id": "a",
        "text": "PGP: メールアドレスごと, S/MIME: メールアドレスごと, SMTP over TLS: メールサーバごと"
      },
      {
        "id": "b",
        "text": "PGP: メールアドレスごと, S/MIME: メールサーバごと, SMTP over TLS: メールアドレスごと"
      },
      {
        "id": "c",
        "text": "PGP: メールサーバごと, S/MIME: メールアドレスごと, SMTP over TLS: メールアドレスごと"
      },
      {
        "id": "d",
        "text": "PGP: メールサーバごと, S/MIME: メールサーバごと, SMTP over TLS: メールサーバごと"
      }
    ],
    "correctOption": null,
    "subCategory": "その他"
  },
  {
    "qNo": 17,
    "text": "無線 LAN のアクセスポイントがもつプライバシーセパレータ機能 (アクセスポイントアイソレーション) の説明はどれか。",
    "options": [
      {
        "id": "a",
        "text": "アクセスポイントの識別子を知っている利用者だけに機器の接続を許可する。"
      },
      {
        "id": "b",
        "text": "同じアクセスポイントに無線で接続している機器同士の通信を禁止する。"
      },
      {
        "id": "c",
        "text": "事前に登録された MAC アドレスをもつ機器だけに無線 LAN への接続を許可する。"
      },
      {
        "id": "d",
        "text": "建物外への無線 LAN 電波の漏れを防ぐことによって第三者による盗聴を防止する。"
      }
    ],
    "correctOption": null,
    "subCategory": "その他"
  },
  {
    "qNo": 18,
    "text": "IPv6 の特徴として、適切なものはどれか。",
    "options": [
      {
        "id": "a",
        "text": "IPv6 アドレスから MAC アドレスを調べる際に ARP を使う。"
      },
      {
        "id": "b",
        "text": "アドレス空間は IPv4 の 2^128 倍である。"
      },
      {
        "id": "c",
        "text": "経路の途中でフラグメンテーションを行うことが可能である。"
      },
      {
        "id": "d",
        "text": "ヘッダーは固定長であり、拡張ヘッダー長は 8 オクテットの整数倍である。"
      }
    ],
    "correctOption": null,
    "subCategory": "その他"
  },
  {
    "qNo": 19,
    "text": "クラス D の IP アドレスを使用するのはどの場合か。",
    "options": [
      {
        "id": "a",
        "text": "端末数が 250 台程度までの比較的小規模なネットワークのホストアドレスを割り振る。"
      },
      {
        "id": "b",
        "text": "端末数が 65,000 台程度の中規模なネットワークのホストアドレスを割り振る。"
      },
      {
        "id": "c",
        "text": "プライベートアドレスを割り振る。"
      },
      {
        "id": "d",
        "text": "マルチキャストアドレスを割り振る。"
      }
    ],
    "correctOption": null,
    "subCategory": "その他"
  },
  {
    "qNo": 20,
    "text": "IP ネットワークにおいて、クライアントの設定を変えることなくデフォルトゲートウェイの障害を回避するために用いられるプロトコルはどれか。",
    "options": [
      {
        "id": "a",
        "text": "RARP"
      },
      {
        "id": "b",
        "text": "RSTP"
      },
      {
        "id": "c",
        "text": "RTSP"
      },
      {
        "id": "d",
        "text": "VRRP"
      }
    ],
    "correctOption": null,
    "subCategory": "その他"
  },
  {
    "qNo": 21,
    "text": "表 R と表 S に対して、次の SQL 文を実行した結果はどれか。[表 R: (X, Y)={ (A001, 10), (A002, 20), (A003, 30), (A005, 50) }, 表 S: (X, Z)={ (A002, 20), (A003, 30), (A004, 40) }, SQL文: SELECT R.X AS A, R.Y AS B, S.X AS C, S.Z AS D FROM R LEFT OUTER JOIN S ON R.X = S.X]",
    "options": [
      {
        "id": "a",
        "text": "結果表: (A: A001, B: 10, C: NULL, D: NULL), (A: A005, B: 50, C: NULL, D: NULL)"
      },
      {
        "id": "b",
        "text": "結果表: (A: A002, B: 20, C: A002, D: 20), (A: A003, B: 30, C: A003, D: 30), (A: NULL, B: NULL, C: A004, D: 40)"
      },
      {
        "id": "c",
        "text": "結果表: (A: A001, B: 10, C: NULL, D: NULL), (A: A002, B: 20, C: A002, D: 20), (A: A003, B: 30, C: A003, D: 30), (A: A005, B: 50, C: NULL, D: NULL)"
      },
      {
        "id": "d",
        "text": "結果表: (A: A001, B: 10, C: NULL, D: NULL), (A: A002, B: 20, C: A002, D: 20), (A: A003, B: 30, C: A003, D: 30), (A: NULL, B: NULL, C: A004, D: 40), (A: A005, B: 50, C: NULL, D: NULL)"
      }
    ],
    "correctOption": null,
    "subCategory": "その他"
  },
  {
    "qNo": 22,
    "text": "あるプログラムについて、流れ図で示される部分に関するテストケースを、判定条件網羅 (分岐網羅) によって設定する。この場合のテストケースの組合せとして、適切なものはどれか。ここで、()で囲んだ部分は,一組みのテストケースを表すものとする。[判断条件: A >= 6 or B = 0 を Yes(True) と No(False) で判定]",
    "options": [
      {
        "id": "a",
        "text": "(A=1, B=1), (A=7, B=1)"
      },
      {
        "id": "b",
        "text": "(A=4, B=0), (A=8, B=1)"
      },
      {
        "id": "c",
        "text": "(A=4, B=1), (A=6, B=1)"
      },
      {
        "id": "d",
        "text": "(A=7, B=1), (A=1, B=0)"
      }
    ],
    "correctOption": null,
    "subCategory": "その他"
  },
  {
    "qNo": 23,
    "text": "SDメモリカードに使用される著作権保護技術はどれか。",
    "options": [
      {
        "id": "a",
        "text": "CPPM (Content Protection for Prerecorded Media)"
      },
      {
        "id": "b",
        "text": "CPRM (Content Protection for Recordable Media)"
      },
      {
        "id": "c",
        "text": "DTCP (Digital Transmission Content Protection)"
      },
      {
        "id": "d",
        "text": "HDCP (High-bandwidth Digital Content Protection)"
      }
    ],
    "correctOption": null,
    "subCategory": "その他"
  },
  {
    "qNo": 24,
    "text": "ある業務を新たにシステム化するに当たって、A～D のシステム化案の初期費用, 運用費及びシステム化によって削減される業務費を試算したところ、表のとおりであった。システムの利用期間を 5 年とするとき、最も投資利益率の高いシステム化案はどれか。ここで、投資利益率は次式によって算出する。また、利益の増加額は削減される業務費から投資額を減じたものとし、投資額は初期費用と運用費の合計とする。 投資利益率 = 利益の増加額 ÷ 投資額 [A: 初期費用30, 1年運用費4, 1年削減費25。 B: 初期費用20, 1年運用費6, 1年削減費20。 C: 初期費用20, 1年運用費4, 1年削減費15。 D: 初期費用15, 1年運用費5, 1年削減費22。 (単位:百万円)]",
    "options": [
      {
        "id": "a",
        "text": "A"
      },
      {
        "id": "b",
        "text": "B"
      },
      {
        "id": "c",
        "text": "C"
      },
      {
        "id": "d",
        "text": "D"
      }
    ],
    "correctOption": null,
    "subCategory": "その他"
  },
  {
    "qNo": 25,
    "text": "被監査企業が SaaS をサービス利用契約して業務を実施している場合,被監査企業のシステム監査人が SaaS の利用者環境から SaaS へのアクセスコントロールを評価できる対象の ID はどれか。",
    "options": [
      {
        "id": "a",
        "text": "DBMS の管理者 ID"
      },
      {
        "id": "b",
        "text": "アプリケーションの利用者 ID"
      },
      {
        "id": "c",
        "text": "サーバの OS の利用者 ID"
      },
      {
        "id": "d",
        "text": "ストレージデバイスの管理者 ID"
      }
    ],
    "correctOption": null,
    "subCategory": "その他"
  }
]